setup.py
spouk_tester/__init__.py
spouk_tester/spouk_tester.py
spouk_tester.egg-info/PKG-INFO
spouk_tester.egg-info/SOURCES.txt
spouk_tester.egg-info/dependency_links.txt
spouk_tester.egg-info/top_level.txt
spouk_tester/sub1/__init__.py
spouk_tester/sub1/sub1_lib.py
spouk_tester/sub2/__init__.py
spouk_tester/sub2/sub2_lib.py
spouk_tester/sub3/__init__.py
spouk_tester/sub3/sub3_lib.py