Metadata-Version: 1.0
Name: spouk-tester
Version: 0.1
Summary: This is an Example Package
Home-page: http://example.com/spouk_tester/
Author: ME
Author-email: me@example.com
License: PSF
Keywords: spouk_tester example
Platform: UNKNOWN
